{
  "objective": "Develop implementation strategy for nexus-forge ADK hackathon enhancements based on analyzer findings: 1) Complete ADK Agent2Agent protocol integration 2) Add marketplace and MCP integration 3) Implement swarm intelligence coordination 4) Build visual workflow system 5) Add enterprise features",
  "strategy": "development",
  "mode": "hierarchical",
  "maxAgents": 5,
  "timeout": 180,
  "parallel": true,
  "monitor": true,
  "output": "json",
  "outputDir": "./reports",
  "timestamp": "2025-06-20T04:12:22.374Z",
  "id": "swarm-development-hierarchical-1750392742375"
}